[
	{
		"inputs": [
			{
				"internalType": "string",
				"name": "_name",
				"type": "string"
			},
			{
				"internalType": "string",
				"name": "_description",
				"type": "string"
			},
			{
				"internalType": "uint256",
				"name": "_totalAmount",
				"type": "uint256"
			},
			{
				"internalType": "address[]",
				"name": "_recipients",
				"type": "address[]"
			}
		],
		"name": "createGroup",
		"outputs": [],
		"stateMutability": "nonpayable",
		"type": "function"
	},
	{
		"inputs": [],
		"name": "getAllGroups",
		"outputs": [
			{
				"internalType": "string[]",
				"name": "names",
				"type": "string[]"
			},
			{
				"internalType": "string[]",
				"name": "descriptions",
				"type": "string[]"
			},
			{
				"internalType": "uint256[]",
				"name": "totalAmounts",
				"type": "uint256[]"
			},
			{
				"internalType": "address[][]",
				"name": "allRecipients",
				"type": "address[][]"
			}
		],
		"stateMutability": "view",
		"type": "function"
	},
	{
		"inputs": [],
		"name": "getGroupCount",
		"outputs": [
			{
				"internalType": "uint256",
				"name": "",
				"type": "uint256"
			}
		],
		"stateMutability": "view",
		"type": "function"
	},
	{
		"inputs": [
			{
				"internalType": "uint256",
				"name": "groupId",
				"type": "uint256"
			}
		],
		"name": "getGroupDetailsById",
		"outputs": [
			{
				"internalType": "string",
				"name": "name",
				"type": "string"
			},
			{
				"internalType": "string",
				"name": "description",
				"type": "string"
			},
			{
				"internalType": "uint256",
				"name": "totalAmount",
				"type": "uint256"
			},
			{
				"internalType": "address[]",
				"name": "recipients",
				"type": "address[]"
			}
		],
		"stateMutability": "view",
		"type": "function"
	},
	{
		"inputs": [
			{
				"internalType": "uint256",
				"name": "",
				"type": "uint256"
			}
		],
		"name": "groups",
		"outputs": [
			{
				"internalType": "string",
				"name": "name",
				"type": "string"
			},
			{
				"internalType": "string",
				"name": "description",
				"type": "string"
			},
			{
				"internalType": "uint256",
				"name": "totalAmount",
				"type": "uint256"
			}
		],
		"stateMutability": "view",
		"type": "function"
	}
]